README.rst
setup.py
mob_tools/__init__.py
mob_tools/_better_exceptions.py
mob_tools/_colorama.py
mob_tools/_colorizer.py
mob_tools/_ctime_functions.py
mob_tools/_datetime.py
mob_tools/_defaults.py
mob_tools/_error_interceptor.py
mob_tools/_file_sink.py
mob_tools/_filters.py
mob_tools/_get_frame.py
mob_tools/_handler.py
mob_tools/_locks_machinery.py
mob_tools/_logger.py
mob_tools/_recattrs.py
mob_tools/_simple_sinks.py
mob_tools/_string_parsers.py
mob_tools/generate_mongo_ts.py
mob_tools/get_ent_id.py
mob_tools/inner_ip.py
mob_tools/mobLog.py
mob_tools/mobLogger.py
mob_tools/persist_ent_id.py
mob_tools.egg-info/PKG-INFO
mob_tools.egg-info/SOURCES.txt
mob_tools.egg-info/dependency_links.txt
mob_tools.egg-info/top_level.txt
mob_tools.egg-info/zip-safe