Metadata-Version: 2.1
Name: mob-tools
Version: 0.2.3
Summary: this is a tool package for mobTech.
Home-page: https://github.com/pypa/sampleproject
Author: John
Author-email: zyq9233@163.com
License: MIT
Keywords: mob utils
Classifier: License :: OSI Approved :: MIT License
Classifier: Programming Language :: Python
Classifier: Intended Audience :: Developers
Classifier: Operating System :: OS Independent
